pywincrypt32/__init__.py
pywincrypt32-0.1.0.dist-info/METADATA
pywincrypt32-0.1.0.dist-info/WHEEL
pywincrypt32-0.1.0.dist-info/RECORD
