Metadata-Version: 2.3
Name: pywincrypt32
Version: 0.1.0
Summary: 
License: Apache-2.0
Author: Curtis Ruck
Author-email: curtis@users.github.com
Requires-Python: >=3.9
Classifier: License :: OSI Approved :: Apache Software License
Classifier: Programming Language :: Python :: 3
Classifier: Programming Language :: Python :: 3.9
Classifier: Programming Language :: Python :: 3.10
Classifier: Programming Language :: Python :: 3.11
Classifier: Programming Language :: Python :: 3.12
Classifier: Programming Language :: Python :: 3.13
